{
  "mode": "augment",
  "data_type": "images",
  "path_types": {
    "data": "folders",
    "annotations": "folders"
  },
  "labels_type": "my_ds",
  "frame_w": 800,
  "frame_h": 800,
  "save_location": "/Volumes/TRANSCEND/Data Sets/NewDataSet/Training set/AUG",
  "checkpoint_path": null,
  "data_path": [
    "/Volumes/TRANSCEND/Data Sets/NewDataSet/Training set/Images/MiniDrone",
    "/Volumes/TRANSCEND/Data Sets/NewDataSet/Training set/Images/Okutama",
    "/Volumes/TRANSCEND/Data Sets/NewDataSet/Training set/Images/UFC",
    "/Volumes/TRANSCEND/Data Sets/NewDataSet/Training set/Images/VIRAT",
    "/Volumes/TRANSCEND/Data Sets/NewDataSet/Training set/Images/VisDrone"
  ],
  "labels_path": [
    "/Volumes/TRANSCEND/Data Sets/NewDataSet/Training set/Annotations/MiniDrone",
    "/Volumes/TRANSCEND/Data Sets/NewDataSet/Training set/Annotations/Okutama",
    "/Volumes/TRANSCEND/Data Sets/NewDataSet/Training set/Annotations/UFC",
    "/Volumes/TRANSCEND/Data Sets/NewDataSet/Training set/Annotations/VIRAT",
    "/Volumes/TRANSCEND/Data Sets/NewDataSet/Training set/Annotations/VisDrone"
  ],
  "aug_seq": [
    {
      "name": "FLIP",
      "prob": 0.25
    },
    {
      "name": "HSV",
      "hue": 0,
      "sat": 0,
      "brightness": 50
    },
        {
      "name": "SCALE",
      "scale": 0.3,
      "diff": false
    },
    {
      "name": "TRANSLATE",
      "translate": 0.3,
      "diff": true
    }
  ]
}